<library name="Hardstyle" id="17546">
    <album name="Thunderdome 1997" id="03572">
        <song title="Raveworld" artist="Distortion &amp; MC Raw &amp; Bass D" id="23853"/>
        <song title="Mosquito" artist="Maurizio Braccagni" id="01923"/>
        <song title="We're Gonna Blow Your Mind" artist="Rotterdam Terror Corps" id="13456"/>
    </album>
    <album name="Nepotist" id="00912">
        <song title="Juicy" artist="Illenium" id="45728"/>
        <song title="Glizzy" artist="Hydrocoque" id="23133"/>
        <song title="Jizzy" artist="Hydrocoque &amp; XXXayene" id="99834"/>
        <song title="Hi sisters" artist="James Charles" id="99831">

        </song>
    </album>
</library>